Metadata-Version: 1.0
Name: primeravezpypipackagexample
Version: 0.0.1
Summary: paquete de prueba
Home-page: https://github.com/MicaBergmann/pypipackageexample
Author: Micaela C Bergmann
Author-email: UNKNOWN
License: MIT
Platform: UNKNOWN
